Workbook

Sheet Account Scoring
A1: Account | B1: Ticker | C1: Industry | D1: Sub-Industry | E1: AI Hiring | F1: AI Announce | G1: Cloud | H1: Global | I1: Data Centre | J1: Score | K1: Tier | L1: Last Updated | N1: MODEL WEIGHTS
A2: Microsoft | B2: MSFT | C2: Technology | D2: Software & Internet | E2: 100 | F2: 100 | G2: 100 | H2: 100 | I2: 100 | J2: =ROUND((E2*$O$2+F2*$O$3+G2*$O$4+H2*$O$5+I2*$O$6)/SUM($O$2:$O$6),0) -> 100 | K2: =IF(J2>=80,"Tier 1",IF(J2>=60,"Tier 2","Tier 3")) -> Tier 1 | L2: estimate | N2: AI Hiring | O2: 0.25
A3: Alphabet (Google) | B3: GOOGL | C3: Technology | D3: Software & Internet | E3: 100 | F3: 100 | G3: 98 | H3: 100 | I3: 98 | J3: =ROUND((E3*$O$2+F3*$O$3+G3*$O$4+H3*$O$5+I3*$O$6)/SUM($O$2:$O$6),0) -> 99 | K3: =IF(J3>=80,"Tier 1",IF(J3>=60,"Tier 2","Tier 3")) -> Tier 1 | L3: estimate | N3: AI Announce | O3: 0.25
A4: Amazon | B4: AMZN | C4: Technology | D4: Software & Internet | E4: 100 | F4: 100 | G4: 100 | H4: 98 | I4: 100 | J4: =ROUND((E4*$O$2+F4*$O$3+G4*$O$4+H4*$O$5+I4*$O$6)/SUM($O$2:$O$6),0) -> 100 | K4: =IF(J4>=80,"Tier 1",IF(J4>=60,"Tier 2","Tier 3")) -> Tier 1 | L4: estimate | N4: Cloud | O4: 0.2
A5: Meta Platforms | B5: META | C5: Technology | D5: Software & Internet | E5: 98 | F5: 98 | G5: 88 | H5: 92 | I5: 100 | J5: =ROUND((E5*$O$2+F5*$O$3+G5*$O$4+H5*$O$5+I5*$O$6)/SUM($O$2:$O$6),0) -> 95 | K5: =IF(J5>=80,"Tier 1",IF(J5>=60,"Tier 2","Tier 3")) -> Tier 1 | L5: estimate | N5: Global | O5: 0.2
A6: Apple | B6: AAPL | C6: Technology | D6: Software & Internet | E6: 92 | F6: 96 | G6: 98 | H6: 87 | I6: 67 | J6: =ROUND((E6*$O$2+F6*$O$3+G6*$O$4+H6*$O$5+I6*$O$6)/SUM($O$2:$O$6),0) -> 91 | K6: =IF(J6>=80,"Tier 1",IF(J6>=60,"Tier 2","Tier 3")) -> Tier 1 | L6: estimate | N6: Data Centre | O6: 0.1
A7: Oracle | B7: ORCL | C7: Technology | D7: Software & Internet | E7: 90 | F7: 96 | G7: 96 | H7: 88 | I7: 98 | J7: =ROUND((E7*$O$2+F7*$O$3+G7*$O$4+H7*$O$5+I7*$O$6)/SUM($O$2:$O$6),0) -> 93 | K7: =IF(J7>=80,"Tier 1",IF(J7>=60,"Tier 2","Tier 3")) -> Tier 1 | L7: estimate | N7: Total | O7: =SUM(O2:O6) -> 1
A8: Salesforce | B8: CRM | C8: Technology | D8: Software & Internet | E8: 92 | F8: 96 | G8: 98 | H8: 87 | I8: 67 | J8: =ROUND((E8*$O$2+F8*$O$3+G8*$O$4+H8*$O$5+I8*$O$6)/SUM($O$2:$O$6),0) -> 91 | K8: =IF(J8>=80,"Tier 1",IF(J8>=60,"Tier 2","Tier 3")) -> Tier 1 | L8: estimate
A9: Adobe | B9: ADBE | C9: Technology | D9: Software & Internet | E9: 92 | F9: 96 | G9: 98 | H9: 87 | I9: 67 | J9: =ROUND((E9*$O$2+F9*$O$3+G9*$O$4+H9*$O$5+I9*$O$6)/SUM($O$2:$O$6),0) -> 91 | K9: =IF(J9>=80,"Tier 1",IF(J9>=60,"Tier 2","Tier 3")) -> Tier 1 | L9: estimate
A10: ServiceNow | B10: NOW | C10: Technology | D10: Software & Internet | E10: 92 | F10: 96 | G10: 98 | H10: 75 | I10: 67 | J10: =ROUND((E10*$O$2+F10*$O$3+G10*$O$4+H10*$O$5+I10*$O$6)/SUM($O$2:$O$6),0) -> 88 | K10: =IF(J10>=80,"Tier 1",IF(J10>=60,"Tier 2","Tier 3")) -> Tier 1 | L10: estimate
A11: SAP | B11: SAP | C11: Technology | D11: Software & Internet | E11: 92 | F11: 96 | G11: 98 | H11: 87 | I11: 67 | J11: =ROUND((E11*$O$2+F11*$O$3+G11*$O$4+H11*$O$5+I11*$O$6)/SUM($O$2:$O$6),0) -> 91 | K11: =IF(J11>=80,"Tier 1",IF(J11>=60,"Tier 2","Tier 3")) -> Tier 1 | L11: estimate
A12: Workday | B12: WDAY | C12: Technology | D12: Software & Internet | E12: 86 | F12: 88 | G12: 94 | H12: 75 | I12: 59 | J12: =ROUND((E12*$O$2+F12*$O$3+G12*$O$4+H12*$O$5+I12*$O$6)/SUM($O$2:$O$6),0) -> 83 | K12: =IF(J12>=80,"Tier 1",IF(J12>=60,"Tier 2","Tier 3")) -> Tier 1 | L12: estimate
A13: Snowflake | B13: SNOW | C13: Technology | D13: Software & Internet | E13: 92 | F13: 96 | G13: 98 | H13: 75 | I13: 67 | J13: =ROUND((E13*$O$2+F13*$O$3+G13*$O$4+H13*$O$5+I13*$O$6)/SUM($O$2:$O$6),0) -> 88 | K13: =IF(J13>=80,"Tier 1",IF(J13>=60,"Tier 2","Tier 3")) -> Tier 1 | L13: estimate
A14: Datadog | B14: DDOG | C14: Technology | D14: Software & Internet | E14: 86 | F14: 88 | G14: 94 | H14: 75 | I14: 59 | J14: =ROUND((E14*$O$2+F14*$O$3+G14*$O$4+H14*$O$5+I14*$O$6)/SUM($O$2:$O$6),0) -> 83 | K14: =IF(J14>=80,"Tier 1",IF(J14>=60,"Tier 2","Tier 3")) -> Tier 1 | L14: estimate
A15: Palantir | B15: PLTR | C15: Technology | D15: Software & Internet | E15: 100 | F15: 100 | G15: 100 | H15: 75 | I15: 85 | J15: =ROUND((E15*$O$2+F15*$O$3+G15*$O$4+H15*$O$5+I15*$O$6)/SUM($O$2:$O$6),0) -> 94 | K15: =IF(J15>=80,"Tier 1",IF(J15>=60,"Tier 2","Tier 3")) -> Tier 1 | L15: estimate
A16: Atlassian | B16: TEAM | C16: Technology | D16: Software & Internet | E16: 86 | F16: 88 | G16: 94 | H16: 87 | I16: 59 | J16: =ROUND((E16*$O$2+F16*$O$3+G16*$O$4+H16*$O$5+I16*$O$6)/SUM($O$2:$O$6),0) -> 86 | K16: =IF(J16>=80,"Tier 1",IF(J16>=60,"Tier 2","Tier 3")) -> Tier 1 | L16: estimate
A17: Intuit | B17: INTU | C17: Technology | D17: Software & Internet | E17: 86 | F17: 88 | G17: 94 | H17: 75 | I17: 59 | J17: =ROUND((E17*$O$2+F17*$O$3+G17*$O$4+H17*$O$5+I17*$O$6)/SUM($O$2:$O$6),0) -> 83 | K17: =IF(J17>=80,"Tier 1",IF(J17>=60,"Tier 2","Tier 3")) -> Tier 1 | L17: estimate
A18: Shopify | B18: SHOP | C18: Technology | D18: Software & Internet | E18: 86 | F18: 88 | G18: 94 | H18: 87 | I18: 59 | J18: =ROUND((E18*$O$2+F18*$O$3+G18*$O$4+H18*$O$5+I18*$O$6)/SUM($O$2:$O$6),0) -> 86 | K18: =IF(J18>=80,"Tier 1",IF(J18>=60,"Tier 2","Tier 3")) -> Tier 1 | L18: estimate
A19: Uber | B19: UBER | C19: Technology | D19: Software & Internet | E19: 92 | F19: 96 | G19: 98 | H19: 87 | I19: 67 | J19: =ROUND((E19*$O$2+F19*$O$3+G19*$O$4+H19*$O$5+I19*$O$6)/SUM($O$2:$O$6),0) -> 91 | K19: =IF(J19>=80,"Tier 1",IF(J19>=60,"Tier 2","Tier 3")) -> Tier 1 | L19: estimate
... A162: S&P Global | B162: SPGI | C162: Professional Services | D162: Professional Services | E162: 88 | F162: 88 | G162: 88 | H162: 94 | I162: 50 | J162: =ROUND((E162*$O$2+F162*$O$3+G162*$O$4+H162*$O$5+I162*$O$6)/SUM($O$2:$O$6),0) -> 85 | K162: =IF(J162>=80,"Tier 1",IF(J162>=60,"Tier 2","Tier 3")) -> Tier 1 | L162: estimate

Sheet Dashboard
A1: AI-Ready Account Intelligence — Summary
A2: 161 strategic Americas accounts across 9 industries. Insert a PivotTable on the Accounts table for sub-industry analysis.
A4: Industry | B4: Avg Readiness | C4: Accounts | D4: Tier 1
A5: Technology | B5: =ROUND(AVERAGEIF('Account Scoring'!$C$2:$C$162,A5,'Account Scoring'!$J$2:$J$162),0) -> 89 | C5: =COUNTIF('Account Scoring'!$C$2:$C$162,A5) -> 30 | D5: =COUNTIFS('Account Scoring'!$C$2:$C$162,A5,'Account Scoring'!$K$2:$K$162,"Tier 1") -> 28
A6: Financial Services | B6: =ROUND(AVERAGEIF('Account Scoring'!$C$2:$C$162,A6,'Account Scoring'!$J$2:$J$162),0) -> 75 | C6: =COUNTIF('Account Scoring'!$C$2:$C$162,A6) -> 29 | D6: =COUNTIFS('Account Scoring'!$C$2:$C$162,A6,'Account Scoring'!$K$2:$K$162,"Tier 1") -> 8
A7: Healthcare | B7: =ROUND(AVERAGEIF('Account Scoring'!$C$2:$C$162,A7,'Account Scoring'!$J$2:$J$162),0) -> 72 | C7: =COUNTIF('Account Scoring'!$C$2:$C$162,A7) -> 22 | D7: =COUNTIFS('Account Scoring'!$C$2:$C$162,A7,'Account Scoring'!$K$2:$K$162,"Tier 1") -> 2
A8: Manufacturing & Industrial | B8: =ROUND(AVERAGEIF('Account Scoring'!$C$2:$C$162,A8,'Account Scoring'!$J$2:$J$162),0) -> 74 | C8: =COUNTIF('Account Scoring'!$C$2:$C$162,A8) -> 26 | D8: =COUNTIFS('Account Scoring'!$C$2:$C$162,A8,'Account Scoring'!$K$2:$K$162,"Tier 1") -> 1
A9: Retail & Consumer | B9: =ROUND(AVERAGEIF('Account Scoring'!$C$2:$C$162,A9,'Account Scoring'!$J$2:$J$162),0) -> 67 | C9: =COUNTIF('Account Scoring'!$C$2:$C$162,A9) -> 22 | D9: =COUNTIFS('Account Scoring'!$C$2:$C$162,A9,'Account Scoring'!$K$2:$K$162,"Tier 1") -> 0
A10: Media & Entertainment | B10: =ROUND(AVERAGEIF('Account Scoring'!$C$2:$C$162,A10,'Account Scoring'!$J$2:$J$162),0) -> 75 | C10: =COUNTIF('Account Scoring'!$C$2:$C$162,A10) -> 8 | D10: =COUNTIFS('Account Scoring'!$C$2:$C$162,A10,'Account Scoring'!$K$2:$K$162,"Tier 1") -> 2
A11: Energy & Utilities | B11: =ROUND(AVERAGEIF('Account Scoring'!$C$2:$C$162,A11,'Account Scoring'!$J$2:$J$162),0) -> 64 | C11: =COUNTIF('Account Scoring'!$C$2:$C$162,A11) -> 10 | D11: =COUNTIFS('Account Scoring'!$C$2:$C$162,A11,'Account Scoring'!$K$2:$K$162,"Tier 1") -> 0
A12: Logistics & Transportation | B12: =ROUND(AVERAGEIF('Account Scoring'!$C$2:$C$162,A12,'Account Scoring'!$J$2:$J$162),0) -> 65 | C12: =COUNTIF('Account Scoring'!$C$2:$C$162,A12) -> 8 | D12: =COUNTIFS('Account Scoring'!$C$2:$C$162,A12,'Account Scoring'!$K$2:$K$162,"Tier 1") -> 0
A13: Professional Services | B13: =ROUND(AVERAGEIF('Account Scoring'!$C$2:$C$162,A13,'Account Scoring'!$J$2:$J$162),0) -> 82 | C13: =COUNTIF('Account Scoring'!$C$2:$C$162,A13) -> 6 | D13: =COUNTIFS('Account Scoring'!$C$2:$C$162,A13,'Account Scoring'!$K$2:$K$162,"Tier 1") -> 6
A16: Priority Tier | B16: Accounts
A17: Tier 1 — engage now | B17: =COUNTIF('Account Scoring'!$K$2:$K$162,"Tier 1") -> 47
A18: Tier 2 — nurture | B18: =COUNTIF('Account Scoring'!$K$2:$K$162,"Tier 2") -> 100
A19: Tier 3 — monitor | B19: =COUNTIF('Account Scoring'!$K$2:$K$162,"Tier 3") -> 14

Sheet Read Me
B2: AI-Ready Account Intelligence — Methodology & Data Provenance
B4: IMPORTANT — where the starter numbers come from
B5: Not measured data | C5: The factor scores shipped in this file are ILLUSTRATIVE STARTER VALUES, not researched or scraped figures. Do not present them as measured data.
B6: How they were generated | C6: Each sub-industry has a baseline for the five factors; each company receives an AI-leadership adjustment and a global-footprint adjustment. Hyperscalers and a few AI leaders are hard-set. This makes the model functional immediately.
B7: Replace them | C7: Use the Collector + Updater agents to overwrite the blue input cells with live signals. The Last Updated column shows 'estimate' until a row has been refreshed.
B9: Scoring framework (weights live on Account Scoring, O2:O6)
B10: AI Hiring — 25% | C10: AI / ML / networking engineer openings
B11: AI Announcements — 25% | C11: Investments, partnerships, NVIDIA deals, new AI products
B12: Cloud Presence — 20% | C12: AWS / Azure / GCP adoption depth
B13: Global Footprint — 20% | C13: Countries, global operations, emerging markets
B14: Data Centre Expansion — 10% | C14: Build-out and capacity signals
B15: Tiers | C15: Tier 1 >= 80 (engage now) · Tier 2 60-79 (nurture) · Tier 3 < 60 (monitor)
B17: Self-updating architecture (two agents)
B18: Agent 1 — Collector | C18: Pulls public signals per company (Google News RSS, official IR/press feeds; optional licensed jobs API), scores them, outputs a refresh table. ToS-safe sources only.
B19: Agent 2 — Updater | C19: Runs on a schedule, writes the fresh signals into the blue input cells by matching Ticker, and stamps Last Updated. The workbook's own formulas recompute Score/Tier.
B20: Where it runs | C20: M365-native: Power Automate (scheduled cloud flow) + Office Scripts — perpetual, browser-only, no desktop. Alternative: Python collector on GitHub Actions / a cloud cron.
B21: Honest limit | C21: AI job counts can't be auto-pulled for free (LinkedIn blocks scraping). Use a licensed jobs-data API or keep that one signal manual; everything else auto-refreshes.
B23: Scope
B24: Excluded | C24: Direct network competitors (Cisco, Juniper, Lumen, AT&T, Verizon, NTT, Orange) and pure carriers are excluded — competitive accounts, not sales targets.
B25: Universe | C25: 161 large Americas-relevant enterprises across 9 industries / 16 sub-industries.
